Metadata-Version: 2.4
Name: bitads-v3-core
Version: 0.1.5
Summary: A minimal, testable core for computing BitAds Miner Scores
Author: BitAds Team
License: MIT
Project-URL: Homepage, https://gitlab.com/your-org/bitads-v3
Project-URL: Repository, https://gitlab.com/your-org/bitads-v3
Project-URL: Documentation, https://gitlab.com/your-org/bitads-v3
Keywords: bitads,miner,scoring,blockchain
Classifier: Development Status :: 4 - Beta
Classifier: Intended Audience :: Developers
Classifier: License :: OSI Approved :: MIT License
Classifier: Programming Language :: Python :: 3
Classifier: Programming Language :: Python :: 3.7
Classifier: Programming Language :: Python :: 3.8
Classifier: Programming Language :: Python :: 3.9
Classifier: Programming Language :: Python :: 3.10
Classifier: Programming Language :: Python :: 3.11
Classifier: Topic :: Software Development :: Libraries :: Python Modules
Requires-Python: >=3.7
